chatbotsclient/__init__.py
chatbotsclient/bot.py
chatbotsclient/chatbot.py
chatbotsclient/evaluate.py
chatbotsclient/message.py
chatbotsclient/moderator.py
chatbotsclient/test.py
chatbotsclient-1.0.6.dist-info/LICENCE
chatbotsclient-1.0.6.dist-info/METADATA
chatbotsclient-1.0.6.dist-info/WHEEL
chatbotsclient-1.0.6.dist-info/top_level.txt
chatbotsclient-1.0.6.dist-info/RECORD
